boltdb/__init__.py
boltdb/bucket.py
boltdb/cursor.py
boltdb/db.py
boltdb/freelist.py
boltdb/node.py
boltdb/page.py
boltdb/rwlock.py
boltdb/share.py
boltdb/tx.py
tests/__init__.py
tests/test_bucket.py
tests/test_free.py
tests/test_rw.py
boltdb-0.0.2.dist-info/LICENSE
boltdb-0.0.2.dist-info/METADATA
boltdb-0.0.2.dist-info/WHEEL
boltdb-0.0.2.dist-info/top_level.txt
boltdb-0.0.2.dist-info/RECORD
