Metadata-Version: 2.1
Name: boltdb
Version: 0.0.2
Summary: python port of boltdb
Home-page: https://github.com/qingyunha/pybolt
Author: Tao Qingyun
Author-email: taoqy@ls-a.me
License: UNKNOWN
Platform: UNKNOWN
Classifier: Programming Language :: Python :: 3
Classifier: License :: OSI Approved :: MIT License
Classifier: Operating System :: OS Independent
Requires-Python: >=3.6
